setup.cfg
setup.py
test/test_convert.py
time_aware_polyline/__init__.py
time_aware_polyline/convert.py
time_aware_polyline.egg-info/PKG-INFO
time_aware_polyline.egg-info/SOURCES.txt
time_aware_polyline.egg-info/dependency_links.txt
time_aware_polyline.egg-info/requires.txt
time_aware_polyline.egg-info/top_level.txt