Metadata-Version: 1.1
Name: time-aware-polyline
Version: 0.1.2
Summary: Time aware encoded polyline for geospatial data
Home-page: https://github.com/hypertrack/time-aware-polyline-py
Author: HyperTrack
Author-email: devops@hypertrack.io
License: MIT
Download-URL: https://github.com/hypertrack/time-aware-polyline-py/tarball/0.1
Keywords: geospatial,encoding,polyline
Platform: UNKNOWN
